google/cloud/notebooks/__init__.py
google/cloud/notebooks/gapic_version.py
google/cloud/notebooks/py.typed
google/cloud/notebooks_v1/__init__.py
google/cloud/notebooks_v1/gapic_metadata.json
google/cloud/notebooks_v1/gapic_version.py
google/cloud/notebooks_v1/py.typed
google/cloud/notebooks_v1/services/__init__.py
google/cloud/notebooks_v1/services/managed_notebook_service/__init__.py
google/cloud/notebooks_v1/services/managed_notebook_service/async_client.py
google/cloud/notebooks_v1/services/managed_notebook_service/client.py
google/cloud/notebooks_v1/services/managed_notebook_service/pagers.py
google/cloud/notebooks_v1/services/managed_notebook_service/transports/__init__.py
google/cloud/notebooks_v1/services/managed_notebook_service/transports/base.py
google/cloud/notebooks_v1/services/managed_notebook_service/transports/grpc.py
google/cloud/notebooks_v1/services/managed_notebook_service/transports/grpc_asyncio.py
google/cloud/notebooks_v1/services/notebook_service/__init__.py
google/cloud/notebooks_v1/services/notebook_service/async_client.py
google/cloud/notebooks_v1/services/notebook_service/client.py
google/cloud/notebooks_v1/services/notebook_service/pagers.py
google/cloud/notebooks_v1/services/notebook_service/transports/__init__.py
google/cloud/notebooks_v1/services/notebook_service/transports/base.py
google/cloud/notebooks_v1/services/notebook_service/transports/grpc.py
google/cloud/notebooks_v1/services/notebook_service/transports/grpc_asyncio.py
google/cloud/notebooks_v1/types/__init__.py
google/cloud/notebooks_v1/types/diagnostic_config.py
google/cloud/notebooks_v1/types/environment.py
google/cloud/notebooks_v1/types/event.py
google/cloud/notebooks_v1/types/execution.py
google/cloud/notebooks_v1/types/instance.py
google/cloud/notebooks_v1/types/instance_config.py
google/cloud/notebooks_v1/types/managed_service.py
google/cloud/notebooks_v1/types/runtime.py
google/cloud/notebooks_v1/types/schedule.py
google/cloud/notebooks_v1/types/service.py
google_cloud_notebooks-1.14.0.dist-info/licenses/LICENSE
google_cloud_notebooks-1.14.0.dist-info/METADATA
google_cloud_notebooks-1.14.0.dist-info/WHEEL
google_cloud_notebooks-1.14.0.dist-info/top_level.txt
google_cloud_notebooks-1.14.0.dist-info/RECORD
